[
    {
        "content": "<p>Are there any other beginners on here who would like to work together on trying to learn some category theory?</p>",
        "id": 242399343,
        "sender_full_name": "Josh Lalonde",
        "timestamp": 1623443673
    },
    {
        "content": "<p>I'm a beginner <span aria-label=\"hand\" class=\"emoji emoji-270b\" role=\"img\" title=\"hand\">:hand:</span> have read through 7 Sketches and working through Conceptual Mathematics. What were you thinking?</p>",
        "id": 242414100,
        "sender_full_name": "Fintan Halpenny",
        "timestamp": 1623453229
    },
    {
        "content": "<p>Sounds like you're more advanced than me lol. I'm working my way through R.  F. C. Walters' Categories and Computer Science. I have a copy of Conceptual Mathematics on order. I was thinking of picking a book like one of those and having a regular (say every two weeks) online meetup where we would work through some of the exercises together. But I'm open to other suggestions for format.</p>",
        "id": 242453327,
        "sender_full_name": "Josh Lalonde",
        "timestamp": 1623507785
    },
    {
        "content": "<p>I am also a beginner who has recently read Seven Sketches <span aria-label=\"unicorn\" class=\"emoji emoji-1f984\" role=\"img\" title=\"unicorn\">:unicorn:</span>. Would be happy to join with a few people to read Conceptual Mathematics.</p>",
        "id": 242483803,
        "sender_full_name": "Nick Smith",
        "timestamp": 1623549554
    },
    {
        "content": "<p>I may have gone through more material but I don't feel advanced <span aria-label=\"innocent\" class=\"emoji emoji-1f607\" role=\"img\" title=\"innocent\">:innocent:</span> how is Categories and Computer Science? Myself and some colleagues were thinking of going through that or Category Theory for Computing Science (loving the variation on the titles <span aria-label=\"joy\" class=\"emoji emoji-1f602\" role=\"img\" title=\"joy\">:joy:</span>) , or some others from a list. We haven't decided on anything yet.</p>",
        "id": 242499022,
        "sender_full_name": "Fintan Halpenny",
        "timestamp": 1623574335
    },
    {
        "content": "<p>I'm not sure how much I can commit to anything though. I currently meet with my colleagues once a week on some material, then I also meet another friend once a week and we're going through Introduction to Topology. On top of that I try to fit in Conceptual Mathematics <span aria-label=\"sweat smile\" class=\"emoji emoji-1f605\" role=\"img\" title=\"sweat smile\">:sweat_smile:</span></p>",
        "id": 242499037,
        "sender_full_name": "Fintan Halpenny",
        "timestamp": 1623574410
    },
    {
        "content": "<p>I've found Categories and Computer science quite comprehensible so far, but I think it's a bit elementary in terms of the material that it covers. It's only about halfway through the book that the notion of functors is introduced. I was also recommended Category Theory for Computing Science, so I'd like to check it out too. Feel free to invite your interested colleagues to join in. If we can get 5-10 people signed on then you could drop in whenever you have time.</p>",
        "id": 242521147,
        "sender_full_name": "Josh Lalonde",
        "timestamp": 1623605026
    },
    {
        "content": "<p><span class=\"user-mention\" data-user-id=\"343030\">@Fintan Halpenny</span> <span class=\"user-mention\" data-user-id=\"405946\">@Nick Smith</span> Here's the link to a Discord server where I'm organizing the study group: <a href=\"https://discord.gg/hTEpgYv\">https://discord.gg/hTEpgYv</a> . It's a bit confusing but just go to the #introductions channel and introduce yourself so that I or the server owner can assign you the member role. We can use the channel #self-organized-readings for setting up the group.</p>",
        "id": 242811390,
        "sender_full_name": "Josh Lalonde",
        "timestamp": 1623798848
    },
    {
        "content": "<p>That server seems awfully convoluted for a chat room. Anyway, joined <span aria-label=\"smile\" class=\"emoji emoji-1f642\" role=\"img\" title=\"smile\">:smile:</span></p>",
        "id": 242812359,
        "sender_full_name": "Nick Smith",
        "timestamp": 1623799632
    },
    {
        "content": "<p>I don't see an #introductions channel weirdly enough <span aria-label=\"sweat smile\" class=\"emoji emoji-1f605\" role=\"img\" title=\"sweat smile\">:sweat_smile:</span></p>",
        "id": 242836053,
        "sender_full_name": "Fintan Halpenny",
        "timestamp": 1623825516
    },
    {
        "content": "<p>The #introductions channel is hidden to new users until you post in the other channel you have access to. Then a moderator makes #introductions visible to you. Then after you post in that they make the rest of the channels visible. Hence me calling it \"convoluted\" <span aria-label=\"neutral\" class=\"emoji emoji-1f610\" role=\"img\" title=\"neutral\">:neutral:</span>.</p>",
        "id": 242842191,
        "sender_full_name": "Nick Smith",
        "timestamp": 1623830219
    },
    {
        "content": "<p>I also had to wait 10mins to make any post <span aria-label=\"sweat smile\" class=\"emoji emoji-1f605\" role=\"img\" title=\"sweat smile\">:sweat_smile:</span></p>",
        "id": 242843688,
        "sender_full_name": "Fintan Halpenny",
        "timestamp": 1623831159
    },
    {
        "content": "<p>Hi is this study group still ongoing</p>",
        "id": 265882748,
        "sender_full_name": "Peiyuan Zhu",
        "timestamp": 1640234051
    }
]