[
    {
        "content": "<p>Do we have a current invite link?  Apparently <a href=\"https://twitter.com/_julesh_/status/1242141831057616896\">they keep expiring</a>.</p>\n<div class=\"inline-preview-twitter\"><div class=\"twitter-tweet\"><a href=\"https://twitter.com/_julesh_/status/1242141831057616896\"><img class=\"twitter-avatar\" src=\"https://pbs.twimg.com/profile_images/972424350736486401/RyVTQIgf_normal.jpg\"></a><p>Invite link for a new category theory online space ---v\n\nIntended for everyone from researchers to the curious. (Zulip provides tools for everyone to customise what they see)\n\nFeel free to share this link anywhere you think is appropriate\n<a href=\"https://t.co/lxawahMohc\">https://categorytheory.zulipchat.com/join/f31tmd0bz8zs2lqcgqlsjnsi/</a></p><span>- julesh (@_julesh_)</span></div></div>",
        "id": 198922635,
        "sender_full_name": "Joshua Meyers",
        "timestamp": 1590599495
    },
    {
        "content": "<p><span class=\"user-mention silent\" data-user-id=\"280784\">Joshua Meyers</span> <a href=\"#narrow/stream/229111-general/topic/Invite.20link/near/198922635\">said</a>:</p>\n<blockquote>\n<p>Do we have a current invite link?  Apparently <a href=\"https://twitter.com/_julesh_/status/1242141831057616896\">they keep expiring</a>.</p>\n</blockquote>\n<p><a href=\"join/5vs67zwsr9cwhjxd850ragjm/\">https://categorytheory.zulipchat.com/join/5vs67zwsr9cwhjxd850ragjm/</a></p>",
        "id": 198925282,
        "sender_full_name": "Fabrizio Genovese",
        "timestamp": 1590600798
    },
    {
        "content": "<p>Unfortunately these links expire every 10 days</p>",
        "id": 198925296,
        "sender_full_name": "Fabrizio Genovese",
        "timestamp": 1590600806
    },
    {
        "content": "<p>And there isn't much we can do about it, except making it open access, but we talked about it a few weeks ago and decided it is not necessarily a good idea</p>",
        "id": 198925334,
        "sender_full_name": "Fabrizio Genovese",
        "timestamp": 1590600834
    },
    {
        "content": "<p>Thanks!</p>",
        "id": 198925510,
        "sender_full_name": "Joshua Meyers",
        "timestamp": 1590600922
    },
    {
        "content": "<p>What's the status on invite links? Is there a working one currently?</p>",
        "id": 203590199,
        "sender_full_name": "James Wood",
        "timestamp": 1594462550
    },
    {
        "content": "<p>Invite links can be generated by mods and live for 10 days before self destructing. Here is a fresh one: <a href=\"join/2mjmt3rkgqzne73pg4nwygdz/\">https://categorytheory.zulipchat.com/join/2mjmt3rkgqzne73pg4nwygdz/</a></p>",
        "id": 203590843,
        "sender_full_name": "Jules Hedges",
        "timestamp": 1594463819
    },
    {
        "content": "<p>Cheers!</p>",
        "id": 203591062,
        "sender_full_name": "James Wood",
        "timestamp": 1594464166
    },
    {
        "content": "<p>The one on Azimuth is working now:</p>\n<p><a href=\"https://johncarlosbaez.wordpress.com/2020/03/25/category-theory-community-server/\">https://johncarlosbaez.wordpress.com/2020/03/25/category-theory-community-server/</a></p>\n<p>It will eventually expire... until someone reminds me to get a new one.</p>",
        "id": 203666423,
        "sender_full_name": "John Baez",
        "timestamp": 1594596831
    },
    {
        "content": "<p>Do we have a current invite link?</p>",
        "id": 205730631,
        "sender_full_name": "সায়ন্তন রায়",
        "timestamp": 1596380224
    },
    {
        "content": "<p>The above one doesn't seem to work.</p>",
        "id": 205730644,
        "sender_full_name": "সায়ন্তন রায়",
        "timestamp": 1596380264
    },
    {
        "content": "<p><a href=\"join/crexj49uvyghzyiwjvezf1hl/\">https://categorytheory.zulipchat.com/join/crexj49uvyghzyiwjvezf1hl/</a></p>",
        "id": 205730780,
        "sender_full_name": "Nathanael Arkor",
        "timestamp": 1596380453
    }
]