[
    {
        "content": "<p>I  was writing about this ACT community server running on Zulipchat, which is a lot of words.   Shorter names that came to mind were Zulip forum, Z-forum and ACT forum.  Clearly the latter is most descriptive, so I'll go with that for now.   Just sharing the thought.</p>",
        "id": 200181834,
        "sender_full_name": "David Tanzer",
        "timestamp": 1591677679
    },
    {
        "content": "<p><span class=\"user-mention silent\" data-user-id=\"276143\">David Tanzer</span> <a href=\"#narrow/stream/233322-practice.3A-communication/topic/Nickname.20for.20this.20forum/near/200181834\">said</a>:</p>\n<blockquote>\n<p>Shorter names that came to mind were Zulip forum, Z-forum and ACT forum.  Clearly the latter is most descriptive, so I'll go with that for now. </p>\n</blockquote>\n<p>I'd say the ACT Zulip, because there could potentially be other fora on other platforms in the future.</p>",
        "id": 200184371,
        "sender_full_name": "(=_=)",
        "timestamp": 1591682041
    },
    {
        "content": "<p>That is concise, but idiosyncratic, as most people won't know what a Zulip is.</p>",
        "id": 200187465,
        "sender_full_name": "David Tanzer",
        "timestamp": 1591686067
    },
    {
        "content": "<p>Perhaps then:  the ACT Zulip forum.</p>",
        "id": 200187583,
        "sender_full_name": "David Tanzer",
        "timestamp": 1591686148
    },
    {
        "content": "<p><span class=\"user-mention silent\" data-user-id=\"276143\">David Tanzer</span> <a href=\"#narrow/stream/233322-practice.3A-communication/topic/Nickname.20for.20this.20forum/near/200187465\">said</a>:</p>\n<blockquote>\n<p>That is concise, but idiosyncratic, as most people won't know what a Zulip is.</p>\n</blockquote>\n<p>I'd say the capital Z is a hint to most people that this is a proper noun and, hence, something they should google if they're not familiar with the name. Notice that I've decapitalised the G in Google, because it's now so commonplace to say \"google\" for \"look for something using a search engine\" (like how people used to say \"xerox\", or how we'd say \"scotch tape\") that it seems superfluous to capitalise the word.</p>",
        "id": 200187969,
        "sender_full_name": "(=_=)",
        "timestamp": 1591686538
    },
    {
        "content": "<p>While I am enjoying engaging with applied folks on here, I by no means consider myself an <em>applied</em> category theorist (yet!). Also the heading in the top right just reads \"Category Theory\". So maybe drop the A to be more inclusive?</p>",
        "id": 200200732,
        "sender_full_name": "Morgan Rogers (he/him)",
        "timestamp": 1591695386
    },
    {
        "content": "<p>Yeah, this isn't an ACT forum, it's a CT forum which pretty much has just one channel for ACT</p>",
        "id": 200203882,
        "sender_full_name": "Jules Hedges",
        "timestamp": 1591697418
    },
    {
        "content": "<p>We did discuss making something specifically for ACT right at the beginning. I was against it, I thought ACT was too small</p>",
        "id": 200203927,
        "sender_full_name": "Jules Hedges",
        "timestamp": 1591697474
    },
    {
        "content": "<p>How about the Z-lab    <em>ducks</em></p>",
        "id": 200203969,
        "sender_full_name": "Jules Hedges",
        "timestamp": 1591697516
    },
    {
        "content": "<p>My suggestion would be contracting CATegory theory zuLIP to catlips, if only to see the look on peoples faces when I say it</p>",
        "id": 237986992,
        "sender_full_name": "Ian Price",
        "timestamp": 1620510537
    },
    {
        "content": "<p>The \"official\" name for this place has been the \"Category theory community server\".</p>",
        "id": 237988796,
        "sender_full_name": "John Baez",
        "timestamp": 1620512725
    },
    {
        "content": "<p>But I'm not gonna insist on that.  I do insist that it's about category theory, not just applied category theory.    And I don't see why we need to call it something that contains the brand name \"Zulip\".     That's just the underlying technology.</p>\n<p>Would it be bad to call it the \"category forum\"?    Are there other category forums?</p>",
        "id": 237988936,
        "sender_full_name": "John Baez",
        "timestamp": 1620512884
    },
    {
        "content": "<p>Maybe we don't <em>need</em> to call it something containing \"zulip\", but that's the most natural thing for many people (including myself) to call it, because that's what it is.  I have a much easier time remembering what \"the category theory zulip\" is than \"the category theory community server\".</p>",
        "id": 237989733,
        "sender_full_name": "Mike Shulman",
        "timestamp": 1620513686
    },
    {
        "content": "<p>I always say \"the category theory zulip\".</p>",
        "id": 238045186,
        "sender_full_name": "Joe Moeller",
        "timestamp": 1620576818
    },
    {
        "content": "<p>Same</p>",
        "id": 238053459,
        "sender_full_name": "John van de Wetering",
        "timestamp": 1620586117
    },
    {
        "content": "<p>I just drop the link and say \"here\".</p>",
        "id": 238058971,
        "sender_full_name": "Fabrizio Genovese",
        "timestamp": 1620591661
    }
]