[
    {
        "content": "<p>Does anyone have access to the paper:</p>\n<blockquote>\n<p>Goguen, Joseph. \"Categorical foundations for general systems theory.\" Advances in cybernetics and systems research 1 (1973).</p>\n</blockquote>",
        "id": 592013453,
        "sender_full_name": "Matteo Capucci (he/him)",
        "timestamp": 1777544155
    },
    {
        "content": "<p>This sounds quite like a fascinating paper <span class=\"user-mention\" data-user-id=\"275932\">@Matteo Capucci (he/him)</span> -- have you had any luck finding it? I actually spent 15/20 minutes trying to track it down and apparently I do not think it has been digitized. However, I found that it seems to be present in a copy of the \"Advances in cybernetics and systems research: Proceedings of the European Meeting, Vienna, 1972\" which just so happens to be down the street from me at the MIT Library here in Cambridge!</p>",
        "id": 592115977,
        "sender_full_name": "Jacob S. Zelko",
        "timestamp": 1777569627
    },
    {
        "content": "<p>At this point, I am quite curious about this paper and have read some of Goguen's work in the past so would be interested in reading it myself further. Have you had any luck finding the paper Matteo?</p>",
        "id": 592116042,
        "sender_full_name": "Jacob S. Zelko",
        "timestamp": 1777569650
    },
    {
        "content": "<p>I haven't been able to find it either when I was looking earlier, <a href=\"https://www.kestrel.edu/people/smith/pub/goguen.pdf\">this</a> paper discusses it though, it deals with how Goguen emphasized that  'colimits are how to compose systems.'</p>",
        "id": 592121562,
        "sender_full_name": "V Slicer",
        "timestamp": 1777571150
    },
    {
        "content": "<p>No I haven't that's why I asked here. I don't know even what's in it, but I'm intrigued by the title!</p>",
        "id": 592140620,
        "sender_full_name": "Matteo Capucci (he/him)",
        "timestamp": 1777576787
    },
    {
        "content": "<p><span class=\"user-mention silent\" data-user-id=\"1070312\">V Slicer</span> <a href=\"#narrow/channel/232160-learning.3A-reading-.26-references/topic/Goguen's.20Categorical.20foundations.20for.20general.20systems.20theory/near/592121562\">said</a>:</p>\n<blockquote>\n<p>I haven't been able to find it either when I was looking earlier, <a href=\"https://www.kestrel.edu/people/smith/pub/goguen.pdf\">this</a> paper discusses it though, it deals with how Goguen emphasized that  'colimits are how to compose systems.'</p>\n</blockquote>\n<p>this seems to be citing a different paper, though I wouldn't be surprised if the gist is the same</p>",
        "id": 592140766,
        "sender_full_name": "Matteo Capucci (he/him)",
        "timestamp": 1777576834
    },
    {
        "content": "<p><span class=\"user-mention silent\" data-user-id=\"275932\">Matteo Capucci (he/him)</span> <a href=\"#narrow/channel/232160-learning.3A-reading-.26-references/topic/Goguen.27s.20Categorical.20foundations.20for.20general.20systems.20theory/near/592140620\">said</a>:</p>\n<blockquote>\n<p>No I haven't that's why I asked here. I don't know even what's in it, but I'm intrigued by the title!</p>\n</blockquote>\n<p>Alright, well, then it is settled! I think I shall make this a mini-quest to see if I can find this from the library.</p>",
        "id": 592149800,
        "sender_full_name": "Jacob S. Zelko",
        "timestamp": 1777580041
    },
    {
        "content": "<p>That's be wonderful <span class=\"user-mention\" data-user-id=\"483329\">@Jacob S. Zelko</span> thanks a lot :D</p>",
        "id": 592548379,
        "sender_full_name": "Matteo Capucci (he/him)",
        "timestamp": 1777807227
    },
    {
        "content": "<p>Just a little update here <span class=\"user-mention\" data-user-id=\"275932\">@Matteo Capucci (he/him)</span> : with the help of a friend, we tracked it down in the off-site library archives. We put in a scan request yesterday and should have a scanned copy back by May 27th if not sooner!</p>",
        "id": 593257064,
        "sender_full_name": "Jacob S. Zelko",
        "timestamp": 1778073829
    },
    {
        "content": "<p>Hello, someone (not <span class=\"user-mention\" data-user-id=\"483329\">@Jacob S. Zelko</span>) sent me a scan of the paper, which I found very interesting. However, it's not possible for me to share it. So I digitised it and put it here: <a href=\"https://github.com/mattecapu/goguen-categorical-foundations\">https://github.com/mattecapu/goguen-categorical-foundations</a></p>\n<p>Happy reading! It's a pretty visionary paper.</p>",
        "id": 596166760,
        "sender_full_name": "Matteo Capucci (he/him)",
        "timestamp": 1779197154
    },
    {
        "content": "<p>Oh great <span class=\"user-mention\" data-user-id=\"275932\">@Matteo Capucci (he/him)</span> ! Glad you were able to acquire a copy!</p>\n<p>I started taking a look at this copy too so far and it's always interesting to see Goguen's perspective. I remember reading his <a href=\"https://www.cs.ox.ac.uk/files/3395/PRG72.pdf\">A Categorical Manifesto</a> a year or so ago and found it interesting in his scope of vision.</p>",
        "id": 596265326,
        "sender_full_name": "Jacob S. Zelko",
        "timestamp": 1779218700
    },
    {
        "content": "<p>This paper is pretty interesting as well so far -- the ambition is there. I am on the second page currently and am puttering away with his notion of what he is calling \"<strong>T</strong>-objects\". Have you finished it yet Matteo?</p>",
        "id": 596265545,
        "sender_full_name": "Jacob S. Zelko",
        "timestamp": 1779218760
    },
    {
        "content": "<p>Last sentence of the paper: \"Contemplate <span class=\"katex\"><span class=\"katex-mathml\"><math xmlns=\"http://www.w3.org/1998/Math/MathML\"><semantics><mrow><msubsup><mi>D</mi><mn>0</mn><mi mathvariant=\"normal\">∞</mi></msubsup><mo stretchy=\"false\">(</mo><msub><mi mathvariant=\"bold\">O</mi><mrow><mi mathvariant=\"bold\">N</mi><mo separator=\"true\">,</mo><mi>S</mi><mo stretchy=\"false\">(</mo><mo stretchy=\"false\">[</mo><mn>0</mn><mo separator=\"true\">,</mo><mn>1</mn><mo stretchy=\"false\">)</mo></mrow></msub><mo stretchy=\"false\">)</mo></mrow><annotation encoding=\"application/x-tex\">D^\\infty_0(\\mathbf O_{\\mathbf N, S([0,1)})</annotation></semantics></math></span><span class=\"katex-html\" aria-hidden=\"true\"><span class=\"base\"><span class=\"strut\" style=\"height:1.1052em;vertical-align:-0.3552em;\"></span><span class=\"mord\"><span class=\"mord mathnormal\" style=\"margin-right:0.0278em;\">D</span><span class=\"msupsub\"><span class=\"vlist-t vlist-t2\"><span class=\"vlist-r\"><span class=\"vlist\" style=\"height:0.6644em;\"><span style=\"top:-2.4519em;margin-left:-0.0278em;margin-right:0.05em;\"><span class=\"pstrut\" style=\"height:2.7em;\"></span><span class=\"sizing reset-size6 size3 mtight\"><span class=\"mord mtight\">0</span></span></span><span style=\"top:-3.063em;margin-right:0.05em;\"><span class=\"pstrut\" style=\"height:2.7em;\"></span><span class=\"sizing reset-size6 size3 mtight\"><span class=\"mord mtight\">∞</span></span></span></span><span class=\"vlist-s\">​</span></span><span class=\"vlist-r\"><span class=\"vlist\" style=\"height:0.2481em;\"><span></span></span></span></span></span></span><span class=\"mopen\">(</span><span class=\"mord\"><span class=\"mord mathbf\">O</span><span class=\"msupsub\"><span class=\"vlist-t vlist-t2\"><span class=\"vlist-r\"><span class=\"vlist\" style=\"height:0.3448em;\"><span style=\"top:-2.5198em;margin-left:0em;margin-right:0.05em;\"><span class=\"pstrut\" style=\"height:2.7em;\"></span><span class=\"sizing reset-size6 size3 mtight\"><span class=\"mord mtight\"><span class=\"mord mathbf mtight\">N</span><span class=\"mpunct mtight\">,</span><span class=\"mord mathnormal mtight\" style=\"margin-right:0.0576em;\">S</span><span class=\"mopen mtight\">([</span><span class=\"mord mtight\">0</span><span class=\"mpunct mtight\">,</span><span class=\"mord mtight\">1</span><span class=\"mclose mtight\">)</span></span></span></span></span><span class=\"vlist-s\">​</span></span><span class=\"vlist-r\"><span class=\"vlist\" style=\"height:0.3552em;\"><span></span></span></span></span></span></span><span class=\"mclose\">)</span></span></span></span>.\"</p>",
        "id": 596293259,
        "sender_full_name": "Joe Moeller",
        "timestamp": 1779227072
    },
    {
        "content": "<p>I can hear the angelic choir</p>",
        "id": 596356224,
        "sender_full_name": "Matteo Capucci (he/him)",
        "timestamp": 1779258149
    },
    {
        "content": "<p><span class=\"user-mention silent\" data-user-id=\"483329\">Jacob S. Zelko</span> <a href=\"#narrow/channel/232160-learning.3A-reading-.26-references/topic/Goguen's.20Categorical.20foundations.20for.20general.20systems.20theory/near/596265545\">said</a>:</p>\n<blockquote>\n<p>Have you finished it yet Matteo?</p>\n</blockquote>\n<p>Yes! I had to read it to copyedit it anyway</p>",
        "id": 596356321,
        "sender_full_name": "Matteo Capucci (he/him)",
        "timestamp": 1779258197
    },
    {
        "content": "<p>a T-object ends up to just he a copresheaf over a category of 'time intervals'</p>",
        "id": 596356400,
        "sender_full_name": "Matteo Capucci (he/him)",
        "timestamp": 1779258231
    },
    {
        "content": "<p>Then he claims these objects interconnect by gluing (colimits) and you can get their behaviour by variable sharing (limits)</p>",
        "id": 596356503,
        "sender_full_name": "Matteo Capucci (he/him)",
        "timestamp": 1779258274
    },
    {
        "content": "<p>The first anticipated by a few decades the idea of composition as colimits which afaik was reintroduced only by Fong and Baez in 2015<br>\nThe second afaik is only ever pondered again by Schultz, Spivak and Vasilakopolou in 2016 (although to much greater depth and focusing on the temporality aspect)<br>\nIn particular the idea that behaviour composes by limit has become a central aspect of DOTS, and now we can cite an eminent precedent! Before we could only gesture at Willems (who understood behavioural systems are very important) and Adam (who wrote his thesis about formalizing Willems with CT).</p>",
        "id": 596357182,
        "sender_full_name": "Matteo Capucci (he/him)",
        "timestamp": 1779258565
    },
    {
        "content": "<p>Thanks for copyediting and sharing <span class=\"user-mention silent\" data-user-id=\"275932\">Matteo Capucci (he/him)</span>!</p>\n<p><span class=\"user-mention silent\" data-user-id=\"275932\">Matteo Capucci (he/him)</span> <a href=\"#narrow/channel/232160-learning.3A-reading-.26-references/topic/Goguen.27s.20Categorical.20foundations.20for.20general.20systems.20theory/near/596357182\">said</a>:</p>\n<blockquote>\n<p>In particular the idea that behaviour composes by limit has become a central aspect of DOTS, and now we can cite an eminent precedent!</p>\n</blockquote>\n<p>Goguen was already articulating aspects of entering the DOTS yoga? That's very much a tradition we're a part of <img alt=\":grothenwoke:\" class=\"emoji\" src=\"https://avatars.zulip.com/21317/emoji/images/4a877e25.png\" title=\"grothenwoke\"></p>",
        "id": 596473493,
        "sender_full_name": "V Slicer",
        "timestamp": 1779287874
    },
    {
        "content": "<p>It's always interesting to come across others in the past exploring these same ideas, recently I encountered some cases where I believe assume-guarantee reasoning might have been anticipated, or differently articulated.</p>",
        "id": 596474762,
        "sender_full_name": "V Slicer",
        "timestamp": 1779288118
    },
    {
        "content": "<p>What does DOTS stand for?</p>",
        "id": 596715737,
        "sender_full_name": "Todd Trimble",
        "timestamp": 1779365154
    },
    {
        "content": "<p>DOTS stands for <em><a href=\"https://matteocapucci.eu/about-dots/\">Double Operadic Theory of Systems</a></em>:</p>\n<blockquote>\n<p>Double Operadic Theory of Systems (DOTS), <em>neé</em> (Doubly) Categorical Systems Theory ((D)CST), is a formal mathematical theory of systems. A <a href=\"https://forest.localcharts.org/st-0001.xml\">theory of systems is the algebra of a double operad</a>: the operations of the operad describe how to compose systems, while the algebra substantiates these operations into actual functors between categories of systems. This structure combines both the <em>compositional</em> and <em>structural</em> aspects of systems theory, with the operad part describing compositionality and the categorical part describing the structure of systems.</p>\n</blockquote>",
        "id": 596719309,
        "sender_full_name": "V Slicer",
        "timestamp": 1779366061
    },
    {
        "content": "<p>It's David Jaz Myers' way of working with decorated/structured cospans, lenses and other open systems in a unified framework, <span class=\"user-mention\" data-user-id=\"277611\">@Todd Trimble</span>.  The ARIA project on safeguarded AI was going to use it, but I'm not sure if that's still true.  There's been a change of leadership.</p>",
        "id": 596808326,
        "sender_full_name": "John Baez",
        "timestamp": 1779386300
    },
    {
        "content": "<p>I'm sorry that I didn't know this.</p>",
        "id": 596815541,
        "sender_full_name": "Todd Trimble",
        "timestamp": 1779388194
    },
    {
        "content": "<p>DOTS is still steaming ahead. Occasionally we even see some T(riple)OTS.</p>",
        "id": 597004865,
        "sender_full_name": "David Corfield",
        "timestamp": 1779456152
    },
    {
        "content": "<p>My excuses if my answer at the time was brief  <span class=\"user-mention\" data-user-id=\"277611\">@Todd Trimble</span>, I was in the middle of writing a longer comment about DOTS in <a href=\"#narrow/channel/274877-community.3A-our-work/topic/Matteo.20Capucci/near/595608965\">this stream</a>, where Matteo shared another paper using DOTS in that stream, but I forgot to link back to it. Thank you for adding that John.</p>",
        "id": 597005044,
        "sender_full_name": "V Slicer",
        "timestamp": 1779456204
    },
    {
        "content": "<p><span class=\"user-mention silent\" data-user-id=\"302507\">David Corfield</span> <a href=\"#narrow/channel/232160-learning.3A-reading-.26-references/topic/Goguen.27s.20Categorical.20foundations.20for.20general.20systems.20theory/near/597004865\">said</a>:</p>\n<blockquote>\n<p>DOTS is still steaming ahead. Occasionally we even see some T(riple)OTS.</p>\n</blockquote>\n<p>Where might one learn more about TOTS? What more is it accounting for over DOTS?</p>",
        "id": 597006823,
        "sender_full_name": "V Slicer",
        "timestamp": 1779456686
    },
    {
        "content": "<p>For an explicit appearance of triple categories in categorical systems theory, try <span class=\"user-mention\" data-user-id=\"275932\">@Matteo Capucci (he/him)</span>'s talk <a href=\"https://www.youtube.com/watch?v=jYxnUy1vH7Q\">Constructing triple categories of cybernetic processes</a>, or more directly, try slides 70-72 of his <a href=\"https://matteocapucci.eu/assets/2022/11/main.pdf\">slides</a>.</p>\n<div class=\"youtube-video message_inline_image\"><a data-id=\"jYxnUy1vH7Q\" href=\"https://www.youtube.com/watch?v=jYxnUy1vH7Q\"><img src=\"https://uploads.zulipusercontent.net/40ad5c8a4d04cd7415b463546ed527a93821b94b/68747470733a2f2f692e7974696d672e636f6d2f76692f6a59786e557931764837512f6d7164656661756c742e6a7067\"></a></div>",
        "id": 597042798,
        "sender_full_name": "David Corfield",
        "timestamp": 1779465671
    },
    {
        "content": "<p>Someday people will joke that only tots use TOTS.   Today is not that day.  But I thought I would defuse the tension.</p>",
        "id": 597279781,
        "sender_full_name": "John Baez",
        "timestamp": 1779520891
    }
]