[
    {
        "content": "<p>You can take a look at the <a href=\"https://agrothendieck.github.io/\">Thèmes pour une harmonie</a> section <em>Picard-Brauer</em> or email me at <a href=\"mailto:carmonamateogm@gmail.com\">carmonamateogm@gmail.com</a> if you want to contribute to it.</p>",
        "id": 245085909,
        "sender_full_name": "Mateo Carmona",
        "timestamp": 1625598960
    },
    {
        "content": "<p>Thank you.</p>",
        "id": 245215419,
        "sender_full_name": "Jade Master",
        "timestamp": 1625679173
    }
]