[
    {
        "content": "<p>There's a sense in which Kan extension is lax-functorial, I am looking for a source or reference in which this is described, I would like to cite a reference for the associativity and unit conditions.</p>",
        "id": 338061861,
        "sender_full_name": "Patrick Nicodemus",
        "timestamp": 1677360167
    },
    {
        "content": "<p>If nobody knows what i'm talking about i'll write it down haha.</p>",
        "id": 338061906,
        "sender_full_name": "Patrick Nicodemus",
        "timestamp": 1677360214
    },
    {
        "content": "<p>I guess the simplest statement is this. Let <span class=\"katex\"><span class=\"katex-mathml\"><math xmlns=\"http://www.w3.org/1998/Math/MathML\"><semantics><mrow><mi>t</mi><mo>:</mo><mi>A</mi><mo>→</mo><mi>B</mi></mrow><annotation encoding=\"application/x-tex\">t : A\\to B</annotation></semantics></math></span><span class=\"katex-html\" aria-hidden=\"true\"><span class=\"base\"><span class=\"strut\" style=\"height:0.6151em;\"></span><span class=\"mord mathnormal\">t</span><span class=\"mspace\" style=\"margin-right:0.2778em;\"></span><span class=\"mrel\">:</span><span class=\"mspace\" style=\"margin-right:0.2778em;\"></span></span><span class=\"base\"><span class=\"strut\" style=\"height:0.6833em;\"></span><span class=\"mord mathnormal\">A</span><span class=\"mspace\" style=\"margin-right:0.2778em;\"></span><span class=\"mrel\">→</span><span class=\"mspace\" style=\"margin-right:0.2778em;\"></span></span><span class=\"base\"><span class=\"strut\" style=\"height:0.6833em;\"></span><span class=\"mord mathnormal\" style=\"margin-right:0.05017em;\">B</span></span></span></span> be a 1-cell in a 2-category.  Let <span class=\"katex\"><span class=\"katex-mathml\"><math xmlns=\"http://www.w3.org/1998/Math/MathML\"><semantics><mrow><mi>H</mi><mi>o</mi><mi>m</mi><mo stretchy=\"false\">(</mo><mi>A</mi><mo separator=\"true\">,</mo><mi>A</mi><mo stretchy=\"false\">)</mo></mrow><annotation encoding=\"application/x-tex\">Hom(A,A)</annotation></semantics></math></span><span class=\"katex-html\" aria-hidden=\"true\"><span class=\"base\"><span class=\"strut\" style=\"height:1em;vertical-align:-0.25em;\"></span><span class=\"mord mathnormal\">Ho</span><span class=\"mord mathnormal\">m</span><span class=\"mopen\">(</span><span class=\"mord mathnormal\">A</span><span class=\"mpunct\">,</span><span class=\"mspace\" style=\"margin-right:0.1667em;\"></span><span class=\"mord mathnormal\">A</span><span class=\"mclose\">)</span></span></span></span> be regarded as the strict monoidal 1-category whose objects are 1-cells and whose morphisms are 2-cells, with monoidal product given by composition. Similarly with <span class=\"katex\"><span class=\"katex-mathml\"><math xmlns=\"http://www.w3.org/1998/Math/MathML\"><semantics><mrow><mi>H</mi><mi>o</mi><mi>m</mi><mo stretchy=\"false\">(</mo><mi>B</mi><mo separator=\"true\">,</mo><mi>B</mi><mo stretchy=\"false\">)</mo></mrow><annotation encoding=\"application/x-tex\">Hom(B,B)</annotation></semantics></math></span><span class=\"katex-html\" aria-hidden=\"true\"><span class=\"base\"><span class=\"strut\" style=\"height:1em;vertical-align:-0.25em;\"></span><span class=\"mord mathnormal\">Ho</span><span class=\"mord mathnormal\">m</span><span class=\"mopen\">(</span><span class=\"mord mathnormal\" style=\"margin-right:0.05017em;\">B</span><span class=\"mpunct\">,</span><span class=\"mspace\" style=\"margin-right:0.1667em;\"></span><span class=\"mord mathnormal\" style=\"margin-right:0.05017em;\">B</span><span class=\"mclose\">)</span></span></span></span>.<br>\nThen there is is a lax monoidal functor from <span class=\"katex\"><span class=\"katex-mathml\"><math xmlns=\"http://www.w3.org/1998/Math/MathML\"><semantics><mrow><mi>H</mi><mi>o</mi><mi>m</mi><mo stretchy=\"false\">(</mo><mi>A</mi><mo separator=\"true\">,</mo><mi>A</mi><mo stretchy=\"false\">)</mo><mo>→</mo><mi>H</mi><mi>o</mi><mi>m</mi><mo stretchy=\"false\">(</mo><mi>B</mi><mo separator=\"true\">,</mo><mi>B</mi><mo stretchy=\"false\">)</mo></mrow><annotation encoding=\"application/x-tex\">Hom(A,A)\\to Hom(B,B)</annotation></semantics></math></span><span class=\"katex-html\" aria-hidden=\"true\"><span class=\"base\"><span class=\"strut\" style=\"height:1em;vertical-align:-0.25em;\"></span><span class=\"mord mathnormal\">Ho</span><span class=\"mord mathnormal\">m</span><span class=\"mopen\">(</span><span class=\"mord mathnormal\">A</span><span class=\"mpunct\">,</span><span class=\"mspace\" style=\"margin-right:0.1667em;\"></span><span class=\"mord mathnormal\">A</span><span class=\"mclose\">)</span><span class=\"mspace\" style=\"margin-right:0.2778em;\"></span><span class=\"mrel\">→</span><span class=\"mspace\" style=\"margin-right:0.2778em;\"></span></span><span class=\"base\"><span class=\"strut\" style=\"height:1em;vertical-align:-0.25em;\"></span><span class=\"mord mathnormal\">Ho</span><span class=\"mord mathnormal\">m</span><span class=\"mopen\">(</span><span class=\"mord mathnormal\" style=\"margin-right:0.05017em;\">B</span><span class=\"mpunct\">,</span><span class=\"mspace\" style=\"margin-right:0.1667em;\"></span><span class=\"mord mathnormal\" style=\"margin-right:0.05017em;\">B</span><span class=\"mclose\">)</span></span></span></span> sending <span class=\"katex\"><span class=\"katex-mathml\"><math xmlns=\"http://www.w3.org/1998/Math/MathML\"><semantics><mrow><mi>x</mi><mo>:</mo><mi>A</mi><mo>→</mo><mi>A</mi></mrow><annotation encoding=\"application/x-tex\">x: A\\to A</annotation></semantics></math></span><span class=\"katex-html\" aria-hidden=\"true\"><span class=\"base\"><span class=\"strut\" style=\"height:0.4306em;\"></span><span class=\"mord mathnormal\">x</span><span class=\"mspace\" style=\"margin-right:0.2778em;\"></span><span class=\"mrel\">:</span><span class=\"mspace\" style=\"margin-right:0.2778em;\"></span></span><span class=\"base\"><span class=\"strut\" style=\"height:0.6833em;\"></span><span class=\"mord mathnormal\">A</span><span class=\"mspace\" style=\"margin-right:0.2778em;\"></span><span class=\"mrel\">→</span><span class=\"mspace\" style=\"margin-right:0.2778em;\"></span></span><span class=\"base\"><span class=\"strut\" style=\"height:0.6833em;\"></span><span class=\"mord mathnormal\">A</span></span></span></span> to the right Kan extension of <span class=\"katex\"><span class=\"katex-mathml\"><math xmlns=\"http://www.w3.org/1998/Math/MathML\"><semantics><mrow><mi>t</mi><mi>x</mi></mrow><annotation encoding=\"application/x-tex\">tx</annotation></semantics></math></span><span class=\"katex-html\" aria-hidden=\"true\"><span class=\"base\"><span class=\"strut\" style=\"height:0.6151em;\"></span><span class=\"mord mathnormal\">t</span><span class=\"mord mathnormal\">x</span></span></span></span> along <span class=\"katex\"><span class=\"katex-mathml\"><math xmlns=\"http://www.w3.org/1998/Math/MathML\"><semantics><mrow><mi>t</mi></mrow><annotation encoding=\"application/x-tex\">t</annotation></semantics></math></span><span class=\"katex-html\" aria-hidden=\"true\"><span class=\"base\"><span class=\"strut\" style=\"height:0.6151em;\"></span><span class=\"mord mathnormal\">t</span></span></span></span>.</p>",
        "id": 338062271,
        "sender_full_name": "Patrick Nicodemus",
        "timestamp": 1677360499
    },
    {
        "content": "<p>Essentially the same observation is made in <a href=\"https://math.stackexchange.com/questions/651158/a-functor-sending-monads-to-monads\">this Math.StackExchange question</a>, though no-one was able to provide a literature reference.</p>",
        "id": 338065781,
        "sender_full_name": "Nathanael Arkor",
        "timestamp": 1677363239
    },
    {
        "content": "<p><span class=\"user-mention\" data-user-id=\"282822\">@fosco</span> Did you ever end up finding a reference lol</p>",
        "id": 338066842,
        "sender_full_name": "Patrick Nicodemus",
        "timestamp": 1677364011
    },
    {
        "content": "<p>Something that is kind of interesting about this:<br>\nPJ Huber has a paper very early on in the history of monads where he observes that if T is a monad on D, and we have an adjunction L : C -&gt; D, R : D -&gt; C with L -| R, then LTR is a monad on C, i.e., we can transfer the monad from D to C along the adjunction. The usual observation that an adjunction between L and R gives rise to a monad on C is just the special case of T = id_D. Somehow Huber's way of phrasing it - \"monads can be transferred along adjunctions\" is always less emphasized in the literature than the special case of the identity monad. </p>\n<p>Something similar seems to be happening here. Everybody cares about the codensity monad, which is what Fosco is asking about when the original monad is the identity monad, but we cannot even find a source for the more general case.</p>",
        "id": 338067144,
        "sender_full_name": "Patrick Nicodemus",
        "timestamp": 1677364253
    },
    {
        "content": "<blockquote>\n<p>Somehow Huber's way of phrasing it - \"monads can be transferred along adjunctions\" is always less emphasized in the literature than the special case of the identity monad.</p>\n</blockquote>\n<p>This is because, when every monad admits a resolution (which is true for V-Cat), Huber's observation is a trivial consequence of the fact that adjunctions compose. So the more general statement is only interesting in 2-categories in which not every monad admits a resolution, which is an uncommon setting.</p>",
        "id": 338072874,
        "sender_full_name": "Nathanael Arkor",
        "timestamp": 1677368512
    },
    {
        "content": "<p>Similarly, when every monad admits a codensity monad (which in particular follows when every monad admits a resolution), then I believe a special case of this more general codensity construction follows from the usual one.</p>",
        "id": 338073966,
        "sender_full_name": "Nathanael Arkor",
        "timestamp": 1677369417
    },
    {
        "content": "<p>In particular, suppose a monad <span class=\"katex\"><span class=\"katex-mathml\"><math xmlns=\"http://www.w3.org/1998/Math/MathML\"><semantics><mrow><mi>t</mi></mrow><annotation encoding=\"application/x-tex\">t</annotation></semantics></math></span><span class=\"katex-html\" aria-hidden=\"true\"><span class=\"base\"><span class=\"strut\" style=\"height:0.6151em;\"></span><span class=\"mord mathnormal\">t</span></span></span></span> on <span class=\"katex\"><span class=\"katex-mathml\"><math xmlns=\"http://www.w3.org/1998/Math/MathML\"><semantics><mrow><mi>C</mi></mrow><annotation encoding=\"application/x-tex\">C</annotation></semantics></math></span><span class=\"katex-html\" aria-hidden=\"true\"><span class=\"base\"><span class=\"strut\" style=\"height:0.6833em;\"></span><span class=\"mord mathnormal\" style=\"margin-right:0.07153em;\">C</span></span></span></span> and a right-adjoint 1-cell <span class=\"katex\"><span class=\"katex-mathml\"><math xmlns=\"http://www.w3.org/1998/Math/MathML\"><semantics><mrow><mi>r</mi><mo>:</mo><mi>C</mi><mo>→</mo><mi>D</mi></mrow><annotation encoding=\"application/x-tex\">r : C \\to D</annotation></semantics></math></span><span class=\"katex-html\" aria-hidden=\"true\"><span class=\"base\"><span class=\"strut\" style=\"height:0.4306em;\"></span><span class=\"mord mathnormal\" style=\"margin-right:0.02778em;\">r</span><span class=\"mspace\" style=\"margin-right:0.2778em;\"></span><span class=\"mrel\">:</span><span class=\"mspace\" style=\"margin-right:0.2778em;\"></span></span><span class=\"base\"><span class=\"strut\" style=\"height:0.6833em;\"></span><span class=\"mord mathnormal\" style=\"margin-right:0.07153em;\">C</span><span class=\"mspace\" style=\"margin-right:0.2778em;\"></span><span class=\"mrel\">→</span><span class=\"mspace\" style=\"margin-right:0.2778em;\"></span></span><span class=\"base\"><span class=\"strut\" style=\"height:0.6833em;\"></span><span class=\"mord mathnormal\" style=\"margin-right:0.02778em;\">D</span></span></span></span>, and suppose that <span class=\"katex\"><span class=\"katex-mathml\"><math xmlns=\"http://www.w3.org/1998/Math/MathML\"><semantics><mrow><mi>t</mi></mrow><annotation encoding=\"application/x-tex\">t</annotation></semantics></math></span><span class=\"katex-html\" aria-hidden=\"true\"><span class=\"base\"><span class=\"strut\" style=\"height:0.6151em;\"></span><span class=\"mord mathnormal\">t</span></span></span></span> is the codensity monad of a 1-cell <span class=\"katex\"><span class=\"katex-mathml\"><math xmlns=\"http://www.w3.org/1998/Math/MathML\"><semantics><mrow><mi>u</mi><mo>:</mo><mi>B</mi><mo>→</mo><mi>C</mi></mrow><annotation encoding=\"application/x-tex\">u : B \\to C</annotation></semantics></math></span><span class=\"katex-html\" aria-hidden=\"true\"><span class=\"base\"><span class=\"strut\" style=\"height:0.4306em;\"></span><span class=\"mord mathnormal\">u</span><span class=\"mspace\" style=\"margin-right:0.2778em;\"></span><span class=\"mrel\">:</span><span class=\"mspace\" style=\"margin-right:0.2778em;\"></span></span><span class=\"base\"><span class=\"strut\" style=\"height:0.6833em;\"></span><span class=\"mord mathnormal\" style=\"margin-right:0.05017em;\">B</span><span class=\"mspace\" style=\"margin-right:0.2778em;\"></span><span class=\"mrel\">→</span><span class=\"mspace\" style=\"margin-right:0.2778em;\"></span></span><span class=\"base\"><span class=\"strut\" style=\"height:0.6833em;\"></span><span class=\"mord mathnormal\" style=\"margin-right:0.07153em;\">C</span></span></span></span>. Then, if I haven't got mixed up,</p>\n<p><span class=\"katex-display\"><span class=\"katex\"><span class=\"katex-mathml\"><math xmlns=\"http://www.w3.org/1998/Math/MathML\" display=\"block\"><semantics><mrow><msub><mrow><mi mathvariant=\"normal\">R</mi><mi mathvariant=\"normal\">a</mi><mi mathvariant=\"normal\">n</mi></mrow><mi>r</mi></msub><mo stretchy=\"false\">(</mo><mi>r</mi><mi>t</mi><mo stretchy=\"false\">)</mo><mo>≅</mo><msub><mrow><mi mathvariant=\"normal\">R</mi><mi mathvariant=\"normal\">a</mi><mi mathvariant=\"normal\">n</mi></mrow><mi>r</mi></msub><mo stretchy=\"false\">(</mo><mi>r</mi><mo stretchy=\"false\">(</mo><msub><mrow><mi mathvariant=\"normal\">R</mi><mi mathvariant=\"normal\">a</mi><mi mathvariant=\"normal\">n</mi></mrow><mi>u</mi></msub><mi>u</mi><mo stretchy=\"false\">)</mo><mo stretchy=\"false\">)</mo><mo>≅</mo><msub><mrow><mi mathvariant=\"normal\">R</mi><mi mathvariant=\"normal\">a</mi><mi mathvariant=\"normal\">n</mi></mrow><mi>r</mi></msub><mo stretchy=\"false\">(</mo><msub><mrow><mi mathvariant=\"normal\">R</mi><mi mathvariant=\"normal\">a</mi><mi mathvariant=\"normal\">n</mi></mrow><mi>u</mi></msub><mo stretchy=\"false\">(</mo><mi>r</mi><mi>u</mi><mo stretchy=\"false\">)</mo><mo stretchy=\"false\">)</mo><mo>≅</mo><msub><mrow><mi mathvariant=\"normal\">R</mi><mi mathvariant=\"normal\">a</mi><mi mathvariant=\"normal\">n</mi></mrow><mrow><mi>r</mi><mi>u</mi></mrow></msub><mo stretchy=\"false\">(</mo><mi>r</mi><mi>u</mi><mo stretchy=\"false\">)</mo></mrow><annotation encoding=\"application/x-tex\">\\mathrm{Ran}_r (r t) \\cong \\mathrm{Ran}_r (r (\\mathrm{Ran}_u u)) \\cong \\mathrm{Ran}_r (\\mathrm{Ran}_u (r u)) \\cong \\mathrm{Ran}_{r u} (r u)</annotation></semantics></math></span><span class=\"katex-html\" aria-hidden=\"true\"><span class=\"base\"><span class=\"strut\" style=\"height:1em;vertical-align:-0.25em;\"></span><span class=\"mord\"><span class=\"mord\"><span class=\"mord mathrm\">Ran</span></span><span class=\"msupsub\"><span class=\"vlist-t vlist-t2\"><span class=\"vlist-r\"><span class=\"vlist\" style=\"height:0.1514em;\"><span style=\"top:-2.55em;margin-right:0.05em;\"><span class=\"pstrut\" style=\"height:2.7em;\"></span><span class=\"sizing reset-size6 size3 mtight\"><span class=\"mord mathnormal mtight\" style=\"margin-right:0.02778em;\">r</span></span></span></span><span class=\"vlist-s\">​</span></span><span class=\"vlist-r\"><span class=\"vlist\" style=\"height:0.15em;\"><span></span></span></span></span></span></span><span class=\"mopen\">(</span><span class=\"mord mathnormal\" style=\"margin-right:0.02778em;\">r</span><span class=\"mord mathnormal\">t</span><span class=\"mclose\">)</span><span class=\"mspace\" style=\"margin-right:0.2778em;\"></span><span class=\"mrel\">≅</span><span class=\"mspace\" style=\"margin-right:0.2778em;\"></span></span><span class=\"base\"><span class=\"strut\" style=\"height:1em;vertical-align:-0.25em;\"></span><span class=\"mord\"><span class=\"mord\"><span class=\"mord mathrm\">Ran</span></span><span class=\"msupsub\"><span class=\"vlist-t vlist-t2\"><span class=\"vlist-r\"><span class=\"vlist\" style=\"height:0.1514em;\"><span style=\"top:-2.55em;margin-right:0.05em;\"><span class=\"pstrut\" style=\"height:2.7em;\"></span><span class=\"sizing reset-size6 size3 mtight\"><span class=\"mord mathnormal mtight\" style=\"margin-right:0.02778em;\">r</span></span></span></span><span class=\"vlist-s\">​</span></span><span class=\"vlist-r\"><span class=\"vlist\" style=\"height:0.15em;\"><span></span></span></span></span></span></span><span class=\"mopen\">(</span><span class=\"mord mathnormal\" style=\"margin-right:0.02778em;\">r</span><span class=\"mopen\">(</span><span class=\"mord\"><span class=\"mord\"><span class=\"mord mathrm\">Ran</span></span><span class=\"msupsub\"><span class=\"vlist-t vlist-t2\"><span class=\"vlist-r\"><span class=\"vlist\" style=\"height:0.1514em;\"><span style=\"top:-2.55em;margin-right:0.05em;\"><span class=\"pstrut\" style=\"height:2.7em;\"></span><span class=\"sizing reset-size6 size3 mtight\"><span class=\"mord mathnormal mtight\">u</span></span></span></span><span class=\"vlist-s\">​</span></span><span class=\"vlist-r\"><span class=\"vlist\" style=\"height:0.15em;\"><span></span></span></span></span></span></span><span class=\"mord mathnormal\">u</span><span class=\"mclose\">))</span><span class=\"mspace\" style=\"margin-right:0.2778em;\"></span><span class=\"mrel\">≅</span><span class=\"mspace\" style=\"margin-right:0.2778em;\"></span></span><span class=\"base\"><span class=\"strut\" style=\"height:1em;vertical-align:-0.25em;\"></span><span class=\"mord\"><span class=\"mord\"><span class=\"mord mathrm\">Ran</span></span><span class=\"msupsub\"><span class=\"vlist-t vlist-t2\"><span class=\"vlist-r\"><span class=\"vlist\" style=\"height:0.1514em;\"><span style=\"top:-2.55em;margin-right:0.05em;\"><span class=\"pstrut\" style=\"height:2.7em;\"></span><span class=\"sizing reset-size6 size3 mtight\"><span class=\"mord mathnormal mtight\" style=\"margin-right:0.02778em;\">r</span></span></span></span><span class=\"vlist-s\">​</span></span><span class=\"vlist-r\"><span class=\"vlist\" style=\"height:0.15em;\"><span></span></span></span></span></span></span><span class=\"mopen\">(</span><span class=\"mord\"><span class=\"mord\"><span class=\"mord mathrm\">Ran</span></span><span class=\"msupsub\"><span class=\"vlist-t vlist-t2\"><span class=\"vlist-r\"><span class=\"vlist\" style=\"height:0.1514em;\"><span style=\"top:-2.55em;margin-right:0.05em;\"><span class=\"pstrut\" style=\"height:2.7em;\"></span><span class=\"sizing reset-size6 size3 mtight\"><span class=\"mord mathnormal mtight\">u</span></span></span></span><span class=\"vlist-s\">​</span></span><span class=\"vlist-r\"><span class=\"vlist\" style=\"height:0.15em;\"><span></span></span></span></span></span></span><span class=\"mopen\">(</span><span class=\"mord mathnormal\" style=\"margin-right:0.02778em;\">r</span><span class=\"mord mathnormal\">u</span><span class=\"mclose\">))</span><span class=\"mspace\" style=\"margin-right:0.2778em;\"></span><span class=\"mrel\">≅</span><span class=\"mspace\" style=\"margin-right:0.2778em;\"></span></span><span class=\"base\"><span class=\"strut\" style=\"height:1em;vertical-align:-0.25em;\"></span><span class=\"mord\"><span class=\"mord\"><span class=\"mord mathrm\">Ran</span></span><span class=\"msupsub\"><span class=\"vlist-t vlist-t2\"><span class=\"vlist-r\"><span class=\"vlist\" style=\"height:0.1514em;\"><span style=\"top:-2.55em;margin-right:0.05em;\"><span class=\"pstrut\" style=\"height:2.7em;\"></span><span class=\"sizing reset-size6 size3 mtight\"><span class=\"mord mtight\"><span class=\"mord mathnormal mtight\" style=\"margin-right:0.02778em;\">r</span><span class=\"mord mathnormal mtight\">u</span></span></span></span></span><span class=\"vlist-s\">​</span></span><span class=\"vlist-r\"><span class=\"vlist\" style=\"height:0.15em;\"><span></span></span></span></span></span></span><span class=\"mopen\">(</span><span class=\"mord mathnormal\" style=\"margin-right:0.02778em;\">r</span><span class=\"mord mathnormal\">u</span><span class=\"mclose\">)</span></span></span></span></span></p>\n<p>so that this construction is the codensity monad of <span class=\"katex\"><span class=\"katex-mathml\"><math xmlns=\"http://www.w3.org/1998/Math/MathML\"><semantics><mrow><mi>r</mi><mi>u</mi></mrow><annotation encoding=\"application/x-tex\">r u</annotation></semantics></math></span><span class=\"katex-html\" aria-hidden=\"true\"><span class=\"base\"><span class=\"strut\" style=\"height:0.4306em;\"></span><span class=\"mord mathnormal\" style=\"margin-right:0.02778em;\">r</span><span class=\"mord mathnormal\">u</span></span></span></span>.</p>",
        "id": 338074408,
        "sender_full_name": "Nathanael Arkor",
        "timestamp": 1677369729
    },
    {
        "content": "<p><del>Therefore, the more general construction is only particularly interesting in 2-categories other than V-Cat.</del></p>",
        "id": 338074499,
        "sender_full_name": "Nathanael Arkor",
        "timestamp": 1677369816
    },
    {
        "content": "<p><span class=\"user-mention\" data-user-id=\"276092\">@Nathanael Arkor</span> why is <span class=\"katex\"><span class=\"katex-mathml\"><math xmlns=\"http://www.w3.org/1998/Math/MathML\"><semantics><mrow><mi>r</mi><mo stretchy=\"false\">(</mo><msub><mrow><mi mathvariant=\"normal\">R</mi><mi mathvariant=\"normal\">a</mi><mi mathvariant=\"normal\">n</mi></mrow><mi>u</mi></msub><mi>u</mi><mo stretchy=\"false\">)</mo><mo>≃</mo><msub><mrow><mi mathvariant=\"normal\">R</mi><mi mathvariant=\"normal\">a</mi><mi mathvariant=\"normal\">n</mi></mrow><mi>u</mi></msub><mo stretchy=\"false\">(</mo><mi>r</mi><mi>u</mi><mo stretchy=\"false\">)</mo></mrow><annotation encoding=\"application/x-tex\">r(\\mathrm{Ran}_{u}u) \\simeq \\mathrm{Ran}_{u}(ru)</annotation></semantics></math></span><span class=\"katex-html\" aria-hidden=\"true\"><span class=\"base\"><span class=\"strut\" style=\"height:1em;vertical-align:-0.25em;\"></span><span class=\"mord mathnormal\" style=\"margin-right:0.02778em;\">r</span><span class=\"mopen\">(</span><span class=\"mord\"><span class=\"mord\"><span class=\"mord mathrm\">Ran</span></span><span class=\"msupsub\"><span class=\"vlist-t vlist-t2\"><span class=\"vlist-r\"><span class=\"vlist\" style=\"height:0.1514em;\"><span style=\"top:-2.55em;margin-right:0.05em;\"><span class=\"pstrut\" style=\"height:2.7em;\"></span><span class=\"sizing reset-size6 size3 mtight\"><span class=\"mord mtight\"><span class=\"mord mathnormal mtight\">u</span></span></span></span></span><span class=\"vlist-s\">​</span></span><span class=\"vlist-r\"><span class=\"vlist\" style=\"height:0.15em;\"><span></span></span></span></span></span></span><span class=\"mord mathnormal\">u</span><span class=\"mclose\">)</span><span class=\"mspace\" style=\"margin-right:0.2778em;\"></span><span class=\"mrel\">≃</span><span class=\"mspace\" style=\"margin-right:0.2778em;\"></span></span><span class=\"base\"><span class=\"strut\" style=\"height:1em;vertical-align:-0.25em;\"></span><span class=\"mord\"><span class=\"mord\"><span class=\"mord mathrm\">Ran</span></span><span class=\"msupsub\"><span class=\"vlist-t vlist-t2\"><span class=\"vlist-r\"><span class=\"vlist\" style=\"height:0.1514em;\"><span style=\"top:-2.55em;margin-right:0.05em;\"><span class=\"pstrut\" style=\"height:2.7em;\"></span><span class=\"sizing reset-size6 size3 mtight\"><span class=\"mord mtight\"><span class=\"mord mathnormal mtight\">u</span></span></span></span></span><span class=\"vlist-s\">​</span></span><span class=\"vlist-r\"><span class=\"vlist\" style=\"height:0.15em;\"><span></span></span></span></span></span></span><span class=\"mopen\">(</span><span class=\"mord mathnormal\" style=\"margin-right:0.02778em;\">r</span><span class=\"mord mathnormal\">u</span><span class=\"mclose\">)</span></span></span></span>?</p>",
        "id": 338195551,
        "sender_full_name": "Christian Williams",
        "timestamp": 1677439398
    },
    {
        "content": "<p>We have <span class=\"katex\"><span class=\"katex-mathml\"><math xmlns=\"http://www.w3.org/1998/Math/MathML\"><semantics><mrow><msub><mrow><mi mathvariant=\"normal\">R</mi><mi mathvariant=\"normal\">a</mi><mi mathvariant=\"normal\">n</mi></mrow><mi>u</mi></msub><mi>u</mi><mo>=</mo><mo>∏</mo><mi>b</mi><mo lspace=\"0em\" rspace=\"0em\">:</mo><mi>B</mi><mtext>  </mtext><mtext>  </mtext><mi>C</mi><mo stretchy=\"false\">(</mo><mo>−</mo><mo separator=\"true\">,</mo><mi>u</mi><mo stretchy=\"false\">(</mo><mi>b</mi><mo stretchy=\"false\">)</mo><mo stretchy=\"false\">)</mo><mo>⋔</mo><mi>u</mi><mo stretchy=\"false\">(</mo><mi>b</mi><mo stretchy=\"false\">)</mo></mrow><annotation encoding=\"application/x-tex\">\\mathrm{Ran}_{u}u = \\prod b{:}B\\;\\; C(-,u(b))\\pitchfork u(b)</annotation></semantics></math></span><span class=\"katex-html\" aria-hidden=\"true\"><span class=\"base\"><span class=\"strut\" style=\"height:0.8333em;vertical-align:-0.15em;\"></span><span class=\"mord\"><span class=\"mord\"><span class=\"mord mathrm\">Ran</span></span><span class=\"msupsub\"><span class=\"vlist-t vlist-t2\"><span class=\"vlist-r\"><span class=\"vlist\" style=\"height:0.1514em;\"><span style=\"top:-2.55em;margin-right:0.05em;\"><span class=\"pstrut\" style=\"height:2.7em;\"></span><span class=\"sizing reset-size6 size3 mtight\"><span class=\"mord mtight\"><span class=\"mord mathnormal mtight\">u</span></span></span></span></span><span class=\"vlist-s\">​</span></span><span class=\"vlist-r\"><span class=\"vlist\" style=\"height:0.15em;\"><span></span></span></span></span></span></span><span class=\"mord mathnormal\">u</span><span class=\"mspace\" style=\"margin-right:0.2778em;\"></span><span class=\"mrel\">=</span><span class=\"mspace\" style=\"margin-right:0.2778em;\"></span></span><span class=\"base\"><span class=\"strut\" style=\"height:1em;vertical-align:-0.25em;\"></span><span class=\"mop op-symbol small-op\" style=\"position:relative;top:0em;\">∏</span><span class=\"mspace\" style=\"margin-right:0.1667em;\"></span><span class=\"mord mathnormal\">b</span><span class=\"mord\"><span class=\"mrel\">:</span></span><span class=\"mord mathnormal\" style=\"margin-right:0.05017em;\">B</span><span class=\"mspace\" style=\"margin-right:0.2778em;\"></span><span class=\"mspace\" style=\"margin-right:0.2778em;\"></span><span class=\"mord mathnormal\" style=\"margin-right:0.07153em;\">C</span><span class=\"mopen\">(</span><span class=\"mord\">−</span><span class=\"mpunct\">,</span><span class=\"mspace\" style=\"margin-right:0.1667em;\"></span><span class=\"mord mathnormal\">u</span><span class=\"mopen\">(</span><span class=\"mord mathnormal\">b</span><span class=\"mclose\">))</span><span class=\"mspace\" style=\"margin-right:0.2778em;\"></span><span class=\"mrel amsrm\">⋔</span><span class=\"mspace\" style=\"margin-right:0.2778em;\"></span></span><span class=\"base\"><span class=\"strut\" style=\"height:1em;vertical-align:-0.25em;\"></span><span class=\"mord mathnormal\">u</span><span class=\"mopen\">(</span><span class=\"mord mathnormal\">b</span><span class=\"mclose\">)</span></span></span></span>, so it is a limit in <span class=\"katex\"><span class=\"katex-mathml\"><math xmlns=\"http://www.w3.org/1998/Math/MathML\"><semantics><mrow><mo stretchy=\"false\">[</mo><mi>C</mi><mo separator=\"true\">,</mo><mi>C</mi><mo stretchy=\"false\">]</mo></mrow><annotation encoding=\"application/x-tex\">[C,C]</annotation></semantics></math></span><span class=\"katex-html\" aria-hidden=\"true\"><span class=\"base\"><span class=\"strut\" style=\"height:1em;vertical-align:-0.25em;\"></span><span class=\"mopen\">[</span><span class=\"mord mathnormal\" style=\"margin-right:0.07153em;\">C</span><span class=\"mpunct\">,</span><span class=\"mspace\" style=\"margin-right:0.1667em;\"></span><span class=\"mord mathnormal\" style=\"margin-right:0.07153em;\">C</span><span class=\"mclose\">]</span></span></span></span>. </p>\n<p>Then are we using that postcomposition <span class=\"katex\"><span class=\"katex-mathml\"><math xmlns=\"http://www.w3.org/1998/Math/MathML\"><semantics><mrow><mi>r</mi><mo>∘</mo><mo>−</mo><mo>:</mo><mo stretchy=\"false\">[</mo><mi>C</mi><mo separator=\"true\">,</mo><mi>C</mi><mo stretchy=\"false\">]</mo><mo>→</mo><mo stretchy=\"false\">[</mo><mi>C</mi><mo separator=\"true\">,</mo><mi>D</mi><mo stretchy=\"false\">]</mo></mrow><annotation encoding=\"application/x-tex\">r\\circ - : [C,C]\\to [C,D]</annotation></semantics></math></span><span class=\"katex-html\" aria-hidden=\"true\"><span class=\"base\"><span class=\"strut\" style=\"height:0.4445em;\"></span><span class=\"mord mathnormal\" style=\"margin-right:0.02778em;\">r</span><span class=\"mspace\" style=\"margin-right:0.2222em;\"></span><span class=\"mbin\">∘</span><span class=\"mspace\" style=\"margin-right:0.2222em;\"></span></span><span class=\"base\"><span class=\"strut\" style=\"height:0.6667em;vertical-align:-0.0833em;\"></span><span class=\"mord\">−</span><span class=\"mspace\" style=\"margin-right:0.2778em;\"></span><span class=\"mrel\">:</span><span class=\"mspace\" style=\"margin-right:0.2778em;\"></span></span><span class=\"base\"><span class=\"strut\" style=\"height:1em;vertical-align:-0.25em;\"></span><span class=\"mopen\">[</span><span class=\"mord mathnormal\" style=\"margin-right:0.07153em;\">C</span><span class=\"mpunct\">,</span><span class=\"mspace\" style=\"margin-right:0.1667em;\"></span><span class=\"mord mathnormal\" style=\"margin-right:0.07153em;\">C</span><span class=\"mclose\">]</span><span class=\"mspace\" style=\"margin-right:0.2778em;\"></span><span class=\"mrel\">→</span><span class=\"mspace\" style=\"margin-right:0.2778em;\"></span></span><span class=\"base\"><span class=\"strut\" style=\"height:1em;vertical-align:-0.25em;\"></span><span class=\"mopen\">[</span><span class=\"mord mathnormal\" style=\"margin-right:0.07153em;\">C</span><span class=\"mpunct\">,</span><span class=\"mspace\" style=\"margin-right:0.1667em;\"></span><span class=\"mord mathnormal\" style=\"margin-right:0.02778em;\">D</span><span class=\"mclose\">]</span></span></span></span> is a right adjoint, and so preserves limits? Because if <span class=\"katex\"><span class=\"katex-mathml\"><math xmlns=\"http://www.w3.org/1998/Math/MathML\"><semantics><mrow><mi>r</mi></mrow><annotation encoding=\"application/x-tex\">r</annotation></semantics></math></span><span class=\"katex-html\" aria-hidden=\"true\"><span class=\"base\"><span class=\"strut\" style=\"height:0.4306em;\"></span><span class=\"mord mathnormal\" style=\"margin-right:0.02778em;\">r</span></span></span></span> is an arbitrary 1-cell, then that means assuming the existence of left lifts. Maybe that's a part of your assumption about the existence of \"resolutions\"; I'm not sure.</p>",
        "id": 338197598,
        "sender_full_name": "Christian Williams",
        "timestamp": 1677440545
    },
    {
        "content": "<p><span class=\"user-mention silent\" data-user-id=\"424412\">Patrick Nicodemus</span> <a href=\"#narrow/stream/229136-theory.3A-category-theory/topic/Kan.20extension.20as.20lax-functorial/near/338062271\">said</a>:</p>\n<blockquote>\n<p>I guess the simplest statement is this. Let <span class=\"katex\"><span class=\"katex-mathml\"><math xmlns=\"http://www.w3.org/1998/Math/MathML\"><semantics><mrow><mi>t</mi><mo>:</mo><mi>A</mi><mo>→</mo><mi>B</mi></mrow><annotation encoding=\"application/x-tex\">t : A\\to B</annotation></semantics></math></span><span class=\"katex-html\" aria-hidden=\"true\"><span class=\"base\"><span class=\"strut\" style=\"height:0.6151em;\"></span><span class=\"mord mathnormal\">t</span><span class=\"mspace\" style=\"margin-right:0.2778em;\"></span><span class=\"mrel\">:</span><span class=\"mspace\" style=\"margin-right:0.2778em;\"></span></span><span class=\"base\"><span class=\"strut\" style=\"height:0.6833em;\"></span><span class=\"mord mathnormal\">A</span><span class=\"mspace\" style=\"margin-right:0.2778em;\"></span><span class=\"mrel\">→</span><span class=\"mspace\" style=\"margin-right:0.2778em;\"></span></span><span class=\"base\"><span class=\"strut\" style=\"height:0.6833em;\"></span><span class=\"mord mathnormal\" style=\"margin-right:0.05017em;\">B</span></span></span></span> be a 1-cell in a 2-category.  Let <span class=\"katex\"><span class=\"katex-mathml\"><math xmlns=\"http://www.w3.org/1998/Math/MathML\"><semantics><mrow><mi>H</mi><mi>o</mi><mi>m</mi><mo stretchy=\"false\">(</mo><mi>A</mi><mo separator=\"true\">,</mo><mi>A</mi><mo stretchy=\"false\">)</mo></mrow><annotation encoding=\"application/x-tex\">Hom(A,A)</annotation></semantics></math></span><span class=\"katex-html\" aria-hidden=\"true\"><span class=\"base\"><span class=\"strut\" style=\"height:1em;vertical-align:-0.25em;\"></span><span class=\"mord mathnormal\">Ho</span><span class=\"mord mathnormal\">m</span><span class=\"mopen\">(</span><span class=\"mord mathnormal\">A</span><span class=\"mpunct\">,</span><span class=\"mspace\" style=\"margin-right:0.1667em;\"></span><span class=\"mord mathnormal\">A</span><span class=\"mclose\">)</span></span></span></span> be regarded as the strict monoidal 1-category whose objects are 1-cells and whose morphisms are 2-cells, with monoidal product given by composition. Similarly with <span class=\"katex\"><span class=\"katex-mathml\"><math xmlns=\"http://www.w3.org/1998/Math/MathML\"><semantics><mrow><mi>H</mi><mi>o</mi><mi>m</mi><mo stretchy=\"false\">(</mo><mi>B</mi><mo separator=\"true\">,</mo><mi>B</mi><mo stretchy=\"false\">)</mo></mrow><annotation encoding=\"application/x-tex\">Hom(B,B)</annotation></semantics></math></span><span class=\"katex-html\" aria-hidden=\"true\"><span class=\"base\"><span class=\"strut\" style=\"height:1em;vertical-align:-0.25em;\"></span><span class=\"mord mathnormal\">Ho</span><span class=\"mord mathnormal\">m</span><span class=\"mopen\">(</span><span class=\"mord mathnormal\" style=\"margin-right:0.05017em;\">B</span><span class=\"mpunct\">,</span><span class=\"mspace\" style=\"margin-right:0.1667em;\"></span><span class=\"mord mathnormal\" style=\"margin-right:0.05017em;\">B</span><span class=\"mclose\">)</span></span></span></span>.<br>\nThen there is is a lax monoidal functor from <span class=\"katex\"><span class=\"katex-mathml\"><math xmlns=\"http://www.w3.org/1998/Math/MathML\"><semantics><mrow><mi>H</mi><mi>o</mi><mi>m</mi><mo stretchy=\"false\">(</mo><mi>A</mi><mo separator=\"true\">,</mo><mi>A</mi><mo stretchy=\"false\">)</mo><mo>→</mo><mi>H</mi><mi>o</mi><mi>m</mi><mo stretchy=\"false\">(</mo><mi>B</mi><mo separator=\"true\">,</mo><mi>B</mi><mo stretchy=\"false\">)</mo></mrow><annotation encoding=\"application/x-tex\">Hom(A,A)\\to Hom(B,B)</annotation></semantics></math></span><span class=\"katex-html\" aria-hidden=\"true\"><span class=\"base\"><span class=\"strut\" style=\"height:1em;vertical-align:-0.25em;\"></span><span class=\"mord mathnormal\">Ho</span><span class=\"mord mathnormal\">m</span><span class=\"mopen\">(</span><span class=\"mord mathnormal\">A</span><span class=\"mpunct\">,</span><span class=\"mspace\" style=\"margin-right:0.1667em;\"></span><span class=\"mord mathnormal\">A</span><span class=\"mclose\">)</span><span class=\"mspace\" style=\"margin-right:0.2778em;\"></span><span class=\"mrel\">→</span><span class=\"mspace\" style=\"margin-right:0.2778em;\"></span></span><span class=\"base\"><span class=\"strut\" style=\"height:1em;vertical-align:-0.25em;\"></span><span class=\"mord mathnormal\">Ho</span><span class=\"mord mathnormal\">m</span><span class=\"mopen\">(</span><span class=\"mord mathnormal\" style=\"margin-right:0.05017em;\">B</span><span class=\"mpunct\">,</span><span class=\"mspace\" style=\"margin-right:0.1667em;\"></span><span class=\"mord mathnormal\" style=\"margin-right:0.05017em;\">B</span><span class=\"mclose\">)</span></span></span></span> sending <span class=\"katex\"><span class=\"katex-mathml\"><math xmlns=\"http://www.w3.org/1998/Math/MathML\"><semantics><mrow><mi>x</mi><mo>:</mo><mi>A</mi><mo>→</mo><mi>A</mi></mrow><annotation encoding=\"application/x-tex\">x: A\\to A</annotation></semantics></math></span><span class=\"katex-html\" aria-hidden=\"true\"><span class=\"base\"><span class=\"strut\" style=\"height:0.4306em;\"></span><span class=\"mord mathnormal\">x</span><span class=\"mspace\" style=\"margin-right:0.2778em;\"></span><span class=\"mrel\">:</span><span class=\"mspace\" style=\"margin-right:0.2778em;\"></span></span><span class=\"base\"><span class=\"strut\" style=\"height:0.6833em;\"></span><span class=\"mord mathnormal\">A</span><span class=\"mspace\" style=\"margin-right:0.2778em;\"></span><span class=\"mrel\">→</span><span class=\"mspace\" style=\"margin-right:0.2778em;\"></span></span><span class=\"base\"><span class=\"strut\" style=\"height:0.6833em;\"></span><span class=\"mord mathnormal\">A</span></span></span></span> to the right Kan extension of <span class=\"katex\"><span class=\"katex-mathml\"><math xmlns=\"http://www.w3.org/1998/Math/MathML\"><semantics><mrow><mi>t</mi><mi>x</mi></mrow><annotation encoding=\"application/x-tex\">tx</annotation></semantics></math></span><span class=\"katex-html\" aria-hidden=\"true\"><span class=\"base\"><span class=\"strut\" style=\"height:0.6151em;\"></span><span class=\"mord mathnormal\">t</span><span class=\"mord mathnormal\">x</span></span></span></span> along <span class=\"katex\"><span class=\"katex-mathml\"><math xmlns=\"http://www.w3.org/1998/Math/MathML\"><semantics><mrow><mi>t</mi></mrow><annotation encoding=\"application/x-tex\">t</annotation></semantics></math></span><span class=\"katex-html\" aria-hidden=\"true\"><span class=\"base\"><span class=\"strut\" style=\"height:0.6151em;\"></span><span class=\"mord mathnormal\">t</span></span></span></span>.</p>\n</blockquote>\n<p>one way to interpret the construction is as a restriction of yoneda structures (cf street-walters) to the analogous \"cayley structures\", where the yoneda embeddings <span class=\"katex\"><span class=\"katex-mathml\"><math xmlns=\"http://www.w3.org/1998/Math/MathML\"><semantics><mrow><mi>A</mi><mo>→</mo><mo stretchy=\"false\">[</mo><msup><mi>A</mi><mi>o</mi></msup><mo separator=\"true\">,</mo><mi>S</mi><mo stretchy=\"false\">]</mo></mrow><annotation encoding=\"application/x-tex\">A\\to [A^o, S]</annotation></semantics></math></span><span class=\"katex-html\" aria-hidden=\"true\"><span class=\"base\"><span class=\"strut\" style=\"height:0.6833em;\"></span><span class=\"mord mathnormal\">A</span><span class=\"mspace\" style=\"margin-right:0.2778em;\"></span><span class=\"mrel\">→</span><span class=\"mspace\" style=\"margin-right:0.2778em;\"></span></span><span class=\"base\"><span class=\"strut\" style=\"height:1em;vertical-align:-0.25em;\"></span><span class=\"mopen\">[</span><span class=\"mord\"><span class=\"mord mathnormal\">A</span><span class=\"msupsub\"><span class=\"vlist-t\"><span class=\"vlist-r\"><span class=\"vlist\" style=\"height:0.6644em;\"><span style=\"top:-3.063em;margin-right:0.05em;\"><span class=\"pstrut\" style=\"height:2.7em;\"></span><span class=\"sizing reset-size6 size3 mtight\"><span class=\"mord mathnormal mtight\">o</span></span></span></span></span></span></span></span><span class=\"mpunct\">,</span><span class=\"mspace\" style=\"margin-right:0.1667em;\"></span><span class=\"mord mathnormal\" style=\"margin-right:0.05764em;\">S</span><span class=\"mclose\">]</span></span></span></span> are replaced by the cayley embeddings <span class=\"katex\"><span class=\"katex-mathml\"><math xmlns=\"http://www.w3.org/1998/Math/MathML\"><semantics><mrow><mi>A</mi><mo>→</mo><mo stretchy=\"false\">[</mo><mi>A</mi><mo separator=\"true\">,</mo><mi>A</mi><mo stretchy=\"false\">]</mo></mrow><annotation encoding=\"application/x-tex\">A\\to [A, A]</annotation></semantics></math></span><span class=\"katex-html\" aria-hidden=\"true\"><span class=\"base\"><span class=\"strut\" style=\"height:0.6833em;\"></span><span class=\"mord mathnormal\">A</span><span class=\"mspace\" style=\"margin-right:0.2778em;\"></span><span class=\"mrel\">→</span><span class=\"mspace\" style=\"margin-right:0.2778em;\"></span></span><span class=\"base\"><span class=\"strut\" style=\"height:1em;vertical-align:-0.25em;\"></span><span class=\"mopen\">[</span><span class=\"mord mathnormal\">A</span><span class=\"mpunct\">,</span><span class=\"mspace\" style=\"margin-right:0.1667em;\"></span><span class=\"mord mathnormal\">A</span><span class=\"mclose\">]</span></span></span></span>. while the former is the abstraction of the 2-category of <span class=\"katex\"><span class=\"katex-mathml\"><math xmlns=\"http://www.w3.org/1998/Math/MathML\"><semantics><mrow><mi>S</mi></mrow><annotation encoding=\"application/x-tex\">S</annotation></semantics></math></span><span class=\"katex-html\" aria-hidden=\"true\"><span class=\"base\"><span class=\"strut\" style=\"height:0.6833em;\"></span><span class=\"mord mathnormal\" style=\"margin-right:0.05764em;\">S</span></span></span></span>-enriched categories, the latter is the abstraction of the 2-category of monoidal categories with their cayley embeddings. (the iso-strength we stumbled on the other day would be an instance where these monoidal categories are categories of monoids, so that each <span class=\"katex\"><span class=\"katex-mathml\"><math xmlns=\"http://www.w3.org/1998/Math/MathML\"><semantics><mrow><mo stretchy=\"false\">[</mo><mi>A</mi><mo separator=\"true\">,</mo><mi>A</mi><mo stretchy=\"false\">]</mo></mrow><annotation encoding=\"application/x-tex\">[A,A]</annotation></semantics></math></span><span class=\"katex-html\" aria-hidden=\"true\"><span class=\"base\"><span class=\"strut\" style=\"height:1em;vertical-align:-0.25em;\"></span><span class=\"mopen\">[</span><span class=\"mord mathnormal\">A</span><span class=\"mpunct\">,</span><span class=\"mspace\" style=\"margin-right:0.1667em;\"></span><span class=\"mord mathnormal\">A</span><span class=\"mclose\">]</span></span></span></span> is a 2-category of representable monads...)</p>\n<p>obviously, having the right kan extensions is a way of saying that the 0-cells are complete. so switching from the yoneda structures to the cayley structures trades-in the assumption that <span class=\"katex\"><span class=\"katex-mathml\"><math xmlns=\"http://www.w3.org/1998/Math/MathML\"><semantics><mrow><mi>S</mi></mrow><annotation encoding=\"application/x-tex\">S</annotation></semantics></math></span><span class=\"katex-html\" aria-hidden=\"true\"><span class=\"base\"><span class=\"strut\" style=\"height:0.6833em;\"></span><span class=\"mord mathnormal\" style=\"margin-right:0.05764em;\">S</span></span></span></span> is total for the assumption that every <span class=\"katex\"><span class=\"katex-mathml\"><math xmlns=\"http://www.w3.org/1998/Math/MathML\"><semantics><mrow><mi>B</mi></mrow><annotation encoding=\"application/x-tex\">B</annotation></semantics></math></span><span class=\"katex-html\" aria-hidden=\"true\"><span class=\"base\"><span class=\"strut\" style=\"height:0.6833em;\"></span><span class=\"mord mathnormal\" style=\"margin-right:0.05017em;\">B</span></span></span></span> is suitably complete. (but \"suitably complete\" might be equivalent with \"total\".) so it is a pricey move. for posets some of the constructions seem to require that the complete lattices be complemented (for duality) and atomic (for size and cogenerators), which by stone duality collapses to <span class=\"katex\"><span class=\"katex-mathml\"><math xmlns=\"http://www.w3.org/1998/Math/MathML\"><semantics><mrow><mi mathvariant=\"script\">S</mi><mi mathvariant=\"script\">e</mi><msup><mi mathvariant=\"script\">t</mi><mi mathvariant=\"script\">o</mi></msup></mrow><annotation encoding=\"application/x-tex\">\\cal Set^o</annotation></semantics></math></span><span class=\"katex-html\" aria-hidden=\"true\"><span class=\"base\"><span class=\"strut\" style=\"height:0.6833em;\"></span><span class=\"mord\"><span class=\"mord mathcal\" style=\"margin-right:0.075em;\">S</span><span class=\"mord mathnormal\">e</span><span class=\"mord\"><span class=\"mord mathnormal\">t</span><span class=\"msupsub\"><span class=\"vlist-t\"><span class=\"vlist-r\"><span class=\"vlist\" style=\"height:0.6644em;\"><span style=\"top:-3.063em;margin-right:0.05em;\"><span class=\"pstrut\" style=\"height:2.7em;\"></span><span class=\"sizing reset-size6 size3 mtight\"><span class=\"mord mathnormal mtight\">o</span></span></span></span></span></span></span></span></span></span></span></span>. for categories the stone duality is... well, makkai has done it, but most of us never succeeded in using it. a host of technical problems seems to explode --- which of course may be worth the price if what you are seeking to axiomatize is even more complicated.</p>\n<p>i am willing to bet that the nontrivial examples will be bicategories, not 2-categories. \"although<br>\nthe fundamental constructions of set theory are categorical, the fundamental constructions of category theory are bicategorical.\"</p>",
        "id": 338200153,
        "sender_full_name": "dusko",
        "timestamp": 1677442178
    },
    {
        "content": "<p>The devil's pitchfork is a powerful tool when working with Kan extensions.</p>\n<p><span class=\"katex\"><span class=\"katex-mathml\"><math xmlns=\"http://www.w3.org/1998/Math/MathML\"><semantics><mrow><mo>⋔</mo></mrow><annotation encoding=\"application/x-tex\">\\pitchfork</annotation></semantics></math></span><span class=\"katex-html\" aria-hidden=\"true\"><span class=\"base\"><span class=\"strut\" style=\"height:0.6922em;\"></span><span class=\"mrel amsrm\">⋔</span></span></span></span> <span aria-label=\"smiling devil\" class=\"emoji emoji-1f608\" role=\"img\" title=\"smiling devil\">:smiling_devil:</span> <span class=\"katex\"><span class=\"katex-mathml\"><math xmlns=\"http://www.w3.org/1998/Math/MathML\"><semantics><mrow><mo>⋔</mo></mrow><annotation encoding=\"application/x-tex\">\\pitchfork</annotation></semantics></math></span><span class=\"katex-html\" aria-hidden=\"true\"><span class=\"base\"><span class=\"strut\" style=\"height:0.6922em;\"></span><span class=\"mrel amsrm\">⋔</span></span></span></span></p>",
        "id": 338200333,
        "sender_full_name": "John Baez",
        "timestamp": 1677442264
    },
    {
        "content": "<p><span class=\"user-mention silent\" data-user-id=\"275899\">Christian Williams</span> <a href=\"#narrow/stream/229136-theory.3A-category-theory/topic/Kan.20extension.20as.20lax-functorial/near/338195551\">said</a>:</p>\n<blockquote>\n<p><span class=\"user-mention silent\" data-user-id=\"276092\">Nathanael Arkor</span> why is <span class=\"katex\"><span class=\"katex-mathml\"><math xmlns=\"http://www.w3.org/1998/Math/MathML\"><semantics><mrow><mi>r</mi><mo stretchy=\"false\">(</mo><msub><mrow><mi mathvariant=\"normal\">R</mi><mi mathvariant=\"normal\">a</mi><mi mathvariant=\"normal\">n</mi></mrow><mi>u</mi></msub><mi>u</mi><mo stretchy=\"false\">)</mo><mo>≃</mo><msub><mrow><mi mathvariant=\"normal\">R</mi><mi mathvariant=\"normal\">a</mi><mi mathvariant=\"normal\">n</mi></mrow><mi>u</mi></msub><mo stretchy=\"false\">(</mo><mi>r</mi><mi>u</mi><mo stretchy=\"false\">)</mo></mrow><annotation encoding=\"application/x-tex\">r(\\mathrm{Ran}_{u}u) \\simeq \\mathrm{Ran}_{u}(ru)</annotation></semantics></math></span><span class=\"katex-html\" aria-hidden=\"true\"><span class=\"base\"><span class=\"strut\" style=\"height:1em;vertical-align:-0.25em;\"></span><span class=\"mord mathnormal\" style=\"margin-right:0.02778em;\">r</span><span class=\"mopen\">(</span><span class=\"mord\"><span class=\"mord\"><span class=\"mord mathrm\">Ran</span></span><span class=\"msupsub\"><span class=\"vlist-t vlist-t2\"><span class=\"vlist-r\"><span class=\"vlist\" style=\"height:0.1514em;\"><span style=\"top:-2.55em;margin-right:0.05em;\"><span class=\"pstrut\" style=\"height:2.7em;\"></span><span class=\"sizing reset-size6 size3 mtight\"><span class=\"mord mtight\"><span class=\"mord mathnormal mtight\">u</span></span></span></span></span><span class=\"vlist-s\">​</span></span><span class=\"vlist-r\"><span class=\"vlist\" style=\"height:0.15em;\"><span></span></span></span></span></span></span><span class=\"mord mathnormal\">u</span><span class=\"mclose\">)</span><span class=\"mspace\" style=\"margin-right:0.2778em;\"></span><span class=\"mrel\">≃</span><span class=\"mspace\" style=\"margin-right:0.2778em;\"></span></span><span class=\"base\"><span class=\"strut\" style=\"height:1em;vertical-align:-0.25em;\"></span><span class=\"mord\"><span class=\"mord\"><span class=\"mord mathrm\">Ran</span></span><span class=\"msupsub\"><span class=\"vlist-t vlist-t2\"><span class=\"vlist-r\"><span class=\"vlist\" style=\"height:0.1514em;\"><span style=\"top:-2.55em;margin-right:0.05em;\"><span class=\"pstrut\" style=\"height:2.7em;\"></span><span class=\"sizing reset-size6 size3 mtight\"><span class=\"mord mtight\"><span class=\"mord mathnormal mtight\">u</span></span></span></span></span><span class=\"vlist-s\">​</span></span><span class=\"vlist-r\"><span class=\"vlist\" style=\"height:0.15em;\"><span></span></span></span></span></span></span><span class=\"mopen\">(</span><span class=\"mord mathnormal\" style=\"margin-right:0.02778em;\">r</span><span class=\"mord mathnormal\">u</span><span class=\"mclose\">)</span></span></span></span>?</p>\n</blockquote>\n<p>We have bijections of 1-cells, natural in <span class=\"katex\"><span class=\"katex-mathml\"><math xmlns=\"http://www.w3.org/1998/Math/MathML\"><semantics><mrow><mi>f</mi></mrow><annotation encoding=\"application/x-tex\">f</annotation></semantics></math></span><span class=\"katex-html\" aria-hidden=\"true\"><span class=\"base\"><span class=\"strut\" style=\"height:0.8889em;vertical-align:-0.1944em;\"></span><span class=\"mord mathnormal\" style=\"margin-right:0.10764em;\">f</span></span></span></span>:</p>\n<ul>\n<li><span class=\"katex\"><span class=\"katex-mathml\"><math xmlns=\"http://www.w3.org/1998/Math/MathML\"><semantics><mrow><mi>f</mi><mo>→</mo><mi>r</mi><msub><mrow><mi mathvariant=\"normal\">R</mi><mi mathvariant=\"normal\">a</mi><mi mathvariant=\"normal\">n</mi></mrow><mi>u</mi></msub><mi>u</mi></mrow><annotation encoding=\"application/x-tex\">f \\to r \\mathrm{Ran}_u u</annotation></semantics></math></span><span class=\"katex-html\" aria-hidden=\"true\"><span class=\"base\"><span class=\"strut\" style=\"height:0.8889em;vertical-align:-0.1944em;\"></span><span class=\"mord mathnormal\" style=\"margin-right:0.10764em;\">f</span><span class=\"mspace\" style=\"margin-right:0.2778em;\"></span><span class=\"mrel\">→</span><span class=\"mspace\" style=\"margin-right:0.2778em;\"></span></span><span class=\"base\"><span class=\"strut\" style=\"height:0.8333em;vertical-align:-0.15em;\"></span><span class=\"mord mathnormal\" style=\"margin-right:0.02778em;\">r</span><span class=\"mord\"><span class=\"mord\"><span class=\"mord mathrm\">Ran</span></span><span class=\"msupsub\"><span class=\"vlist-t vlist-t2\"><span class=\"vlist-r\"><span class=\"vlist\" style=\"height:0.1514em;\"><span style=\"top:-2.55em;margin-right:0.05em;\"><span class=\"pstrut\" style=\"height:2.7em;\"></span><span class=\"sizing reset-size6 size3 mtight\"><span class=\"mord mathnormal mtight\">u</span></span></span></span><span class=\"vlist-s\">​</span></span><span class=\"vlist-r\"><span class=\"vlist\" style=\"height:0.15em;\"><span></span></span></span></span></span></span><span class=\"mord mathnormal\">u</span></span></span></span></li>\n<li><span class=\"katex\"><span class=\"katex-mathml\"><math xmlns=\"http://www.w3.org/1998/Math/MathML\"><semantics><mrow><mi mathvariant=\"normal\">ℓ</mi><mi>f</mi><mo>→</mo><msub><mrow><mi mathvariant=\"normal\">R</mi><mi mathvariant=\"normal\">a</mi><mi mathvariant=\"normal\">n</mi></mrow><mi>u</mi></msub><mi>u</mi></mrow><annotation encoding=\"application/x-tex\">\\ell f \\to \\mathrm{Ran}_u u</annotation></semantics></math></span><span class=\"katex-html\" aria-hidden=\"true\"><span class=\"base\"><span class=\"strut\" style=\"height:0.8889em;vertical-align:-0.1944em;\"></span><span class=\"mord\">ℓ</span><span class=\"mord mathnormal\" style=\"margin-right:0.10764em;\">f</span><span class=\"mspace\" style=\"margin-right:0.2778em;\"></span><span class=\"mrel\">→</span><span class=\"mspace\" style=\"margin-right:0.2778em;\"></span></span><span class=\"base\"><span class=\"strut\" style=\"height:0.8333em;vertical-align:-0.15em;\"></span><span class=\"mord\"><span class=\"mord\"><span class=\"mord mathrm\">Ran</span></span><span class=\"msupsub\"><span class=\"vlist-t vlist-t2\"><span class=\"vlist-r\"><span class=\"vlist\" style=\"height:0.1514em;\"><span style=\"top:-2.55em;margin-right:0.05em;\"><span class=\"pstrut\" style=\"height:2.7em;\"></span><span class=\"sizing reset-size6 size3 mtight\"><span class=\"mord mathnormal mtight\">u</span></span></span></span><span class=\"vlist-s\">​</span></span><span class=\"vlist-r\"><span class=\"vlist\" style=\"height:0.15em;\"><span></span></span></span></span></span></span><span class=\"mord mathnormal\">u</span></span></span></span></li>\n<li><span class=\"katex\"><span class=\"katex-mathml\"><math xmlns=\"http://www.w3.org/1998/Math/MathML\"><semantics><mrow><mi mathvariant=\"normal\">ℓ</mi><mi>f</mi><mi>u</mi><mo>→</mo><mi>u</mi></mrow><annotation encoding=\"application/x-tex\">\\ell f u \\to u</annotation></semantics></math></span><span class=\"katex-html\" aria-hidden=\"true\"><span class=\"base\"><span class=\"strut\" style=\"height:0.8889em;vertical-align:-0.1944em;\"></span><span class=\"mord\">ℓ</span><span class=\"mord mathnormal\" style=\"margin-right:0.10764em;\">f</span><span class=\"mord mathnormal\">u</span><span class=\"mspace\" style=\"margin-right:0.2778em;\"></span><span class=\"mrel\">→</span><span class=\"mspace\" style=\"margin-right:0.2778em;\"></span></span><span class=\"base\"><span class=\"strut\" style=\"height:0.4306em;\"></span><span class=\"mord mathnormal\">u</span></span></span></span></li>\n<li><span class=\"katex\"><span class=\"katex-mathml\"><math xmlns=\"http://www.w3.org/1998/Math/MathML\"><semantics><mrow><mi>f</mi><mi>u</mi><mo>→</mo><mi>r</mi><mi>u</mi></mrow><annotation encoding=\"application/x-tex\">f u \\to r u</annotation></semantics></math></span><span class=\"katex-html\" aria-hidden=\"true\"><span class=\"base\"><span class=\"strut\" style=\"height:0.8889em;vertical-align:-0.1944em;\"></span><span class=\"mord mathnormal\" style=\"margin-right:0.10764em;\">f</span><span class=\"mord mathnormal\">u</span><span class=\"mspace\" style=\"margin-right:0.2778em;\"></span><span class=\"mrel\">→</span><span class=\"mspace\" style=\"margin-right:0.2778em;\"></span></span><span class=\"base\"><span class=\"strut\" style=\"height:0.4306em;\"></span><span class=\"mord mathnormal\" style=\"margin-right:0.02778em;\">r</span><span class=\"mord mathnormal\">u</span></span></span></span></li>\n<li><span class=\"katex\"><span class=\"katex-mathml\"><math xmlns=\"http://www.w3.org/1998/Math/MathML\"><semantics><mrow><mi>f</mi><mo>→</mo><msub><mrow><mi mathvariant=\"normal\">R</mi><mi mathvariant=\"normal\">a</mi><mi mathvariant=\"normal\">n</mi></mrow><mi>u</mi></msub><mo stretchy=\"false\">(</mo><mi>r</mi><mi>u</mi><mo stretchy=\"false\">)</mo></mrow><annotation encoding=\"application/x-tex\">f \\to \\mathrm{Ran}_u (r u)</annotation></semantics></math></span><span class=\"katex-html\" aria-hidden=\"true\"><span class=\"base\"><span class=\"strut\" style=\"height:0.8889em;vertical-align:-0.1944em;\"></span><span class=\"mord mathnormal\" style=\"margin-right:0.10764em;\">f</span><span class=\"mspace\" style=\"margin-right:0.2778em;\"></span><span class=\"mrel\">→</span><span class=\"mspace\" style=\"margin-right:0.2778em;\"></span></span><span class=\"base\"><span class=\"strut\" style=\"height:1em;vertical-align:-0.25em;\"></span><span class=\"mord\"><span class=\"mord\"><span class=\"mord mathrm\">Ran</span></span><span class=\"msupsub\"><span class=\"vlist-t vlist-t2\"><span class=\"vlist-r\"><span class=\"vlist\" style=\"height:0.1514em;\"><span style=\"top:-2.55em;margin-right:0.05em;\"><span class=\"pstrut\" style=\"height:2.7em;\"></span><span class=\"sizing reset-size6 size3 mtight\"><span class=\"mord mathnormal mtight\">u</span></span></span></span><span class=\"vlist-s\">​</span></span><span class=\"vlist-r\"><span class=\"vlist\" style=\"height:0.15em;\"><span></span></span></span></span></span></span><span class=\"mopen\">(</span><span class=\"mord mathnormal\" style=\"margin-right:0.02778em;\">r</span><span class=\"mord mathnormal\">u</span><span class=\"mclose\">)</span></span></span></span></li>\n</ul>",
        "id": 338200928,
        "sender_full_name": "Nathanael Arkor",
        "timestamp": 1677442642
    },
    {
        "content": "<p>nvm, I understand.</p>",
        "id": 338202937,
        "sender_full_name": "Patrick Nicodemus",
        "timestamp": 1677444087
    },
    {
        "content": "<blockquote>\n<p>The manat (ISO code: AZN; sign: ₼; abbreviation: m) is the currency of Azerbaijan. It is subdivided into 100 gapiks.</p>\n</blockquote>",
        "id": 338202961,
        "sender_full_name": "Patrick Nicodemus",
        "timestamp": 1677444102
    },
    {
        "content": "<p>what is <span class=\"katex\"><span class=\"katex-mathml\"><math xmlns=\"http://www.w3.org/1998/Math/MathML\"><semantics><mrow><mi mathvariant=\"normal\">ℓ</mi></mrow><annotation encoding=\"application/x-tex\">\\ell</annotation></semantics></math></span><span class=\"katex-html\" aria-hidden=\"true\"><span class=\"base\"><span class=\"strut\" style=\"height:0.6944em;\"></span><span class=\"mord\">ℓ</span></span></span></span>?</p>",
        "id": 338203286,
        "sender_full_name": "Christian Williams",
        "timestamp": 1677444335
    },
    {
        "content": "<p>if you're assuming that <span class=\"katex\"><span class=\"katex-mathml\"><math xmlns=\"http://www.w3.org/1998/Math/MathML\"><semantics><mrow><mi>r</mi></mrow><annotation encoding=\"application/x-tex\">r</annotation></semantics></math></span><span class=\"katex-html\" aria-hidden=\"true\"><span class=\"base\"><span class=\"strut\" style=\"height:0.4306em;\"></span><span class=\"mord mathnormal\" style=\"margin-right:0.02778em;\">r</span></span></span></span> is a right adjoint, then I understand. but it looked like you said it was an arbitrary morphism.</p>",
        "id": 338203765,
        "sender_full_name": "Christian Williams",
        "timestamp": 1677444653
    },
    {
        "content": "<p>That's true. I confused myself by calling the 1-cell <span class=\"katex\"><span class=\"katex-mathml\"><math xmlns=\"http://www.w3.org/1998/Math/MathML\"><semantics><mrow><mi>r</mi></mrow><annotation encoding=\"application/x-tex\">r</annotation></semantics></math></span><span class=\"katex-html\" aria-hidden=\"true\"><span class=\"base\"><span class=\"strut\" style=\"height:0.4306em;\"></span><span class=\"mord mathnormal\" style=\"margin-right:0.02778em;\">r</span></span></span></span>. I need to think about whether the proof can be adapted to the case when <span class=\"katex\"><span class=\"katex-mathml\"><math xmlns=\"http://www.w3.org/1998/Math/MathML\"><semantics><mrow><mi>r</mi></mrow><annotation encoding=\"application/x-tex\">r</annotation></semantics></math></span><span class=\"katex-html\" aria-hidden=\"true\"><span class=\"base\"><span class=\"strut\" style=\"height:0.4306em;\"></span><span class=\"mord mathnormal\" style=\"margin-right:0.02778em;\">r</span></span></span></span> is an arbitrary 1-cell.</p>",
        "id": 338206473,
        "sender_full_name": "Nathanael Arkor",
        "timestamp": 1677446441
    }
]