[
    {
        "content": "<p>The proceedings of ACT2019 (ie. the one last year) are out! <a href=\"https://arxiv.org/html/2009.06334\">https://arxiv.org/html/2009.06334</a></p>",
        "id": 210259201,
        "sender_full_name": "Jules Hedges",
        "timestamp": 1600262133
    },
    {
        "content": "<p>Hurrah!  It took a huge amount of time for EPTCS to process the submissions.   (One reason: their style file doesn't work.)</p>",
        "id": 210301572,
        "sender_full_name": "John Baez",
        "timestamp": 1600281024
    }
]